{
  "annotations": {
    "list": [
      {
        "builtIn": 1,
        "datasource": {
          "type": "grafana",
          "uid": "-- Grafana --"
        },
        "enable": true,
        "hide": true,
        "iconColor": "rgba(0, 211, 255, 1)",
        "name": "Annotations & Alerts",
        "type": "dashboard"
      }
    ]
  },
  "editable": true,
  "fiscalYearStartMonth": 0,
  "graphTooltip": 0,
  "id": 1,
  "links": [],
  "panels": [
    {
      "datasource": {
        "type": "grafana-postgresql-datasource",
        "uid": "eesjj0teoeebke"
      },
      "fieldConfig": {
        "defaults": {
          "color": {
            "mode": "thresholds"
          },
          "mappings": [],
          "min": -2,
          "thresholds": {
            "mode": "absolute",
            "steps": [
              {
                "color": "green"
              },
              {
                "color": "red",
                "value": 80
              }
            ]
          }
        },
        "overrides": []
      },
      "gridPos": {
        "h": 8,
        "w": 12,
        "x": 0,
        "y": 0
      },
      "id": 3,
      "options": {
        "minVizHeight": 75,
        "minVizWidth": 75,
        "orientation": "auto",
        "reduceOptions": {
          "calcs": [
            "lastNotNull"
          ],
          "fields": "",
          "values": false
        },
        "showThresholdLabels": false,
        "showThresholdMarkers": true,
        "sizing": "auto"
      },
      "pluginVersion": "12.0.2",
      "targets": [
        {
          "editorMode": "code",
          "format": "table",
          "rawQuery": true,
          "rawSql": "SELECT\n  SUM(\"count\") AS clicks_latest_window\nFROM clicks_aggregates\nWHERE window_start = (\n  SELECT MAX(window_start)\n  FROM clicks_aggregates\n);",
          "refId": "A",
          "sql": {
            "columns": [
              {
                "parameters": [],
                "type": "function"
              }
            ],
            "groupBy": [
              {
                "property": {
                  "type": "string"
                },
                "type": "groupBy"
              }
            ],
            "limit": 50
          }
        }
      ],
      "title": "Clicks in Latest Window",
      "type": "gauge"
    },
    {
      "datasource": {
        "type": "grafana-postgresql-datasource",
        "uid": "eesjj0teoeebke"
      },
      "fieldConfig": {
        "defaults": {
          "color": {
            "mode": "palette-classic"
          },
          "custom": {
            "axisBorderShow": false,
            "axisCenteredZero": false,
            "axisColorMode": "text",
            "axisLabel": "",
            "axisPlacement": "auto",
            "barAlignment": 0,
            "barWidthFactor": 0.6,
            "drawStyle": "line",
            "fillOpacity": 0,
            "gradientMode": "none",
            "hideFrom": {
              "legend": false,
              "tooltip": false,
              "viz": false
            },
            "insertNulls": false,
            "lineInterpolation": "linear",
            "lineWidth": 1,
            "pointSize": 5,
            "scaleDistribution": {
              "type": "linear"
            },
            "showPoints": "auto",
            "spanNulls": false,
            "stacking": {
              "group": "A",
              "mode": "none"
            },
            "thresholdsStyle": {
              "mode": "off"
            }
          },
          "mappings": [],
          "thresholds": {
            "mode": "absolute",
            "steps": [
              {
                "color": "green"
              },
              {
                "color": "red",
                "value": 80
              }
            ]
          }
        },
        "overrides": [
          {
            "__systemRef": "hideSeriesFrom",
            "matcher": {
              "id": "byNames",
              "options": {
                "mode": "exclude",
                "names": [
                  "total_clicks"
                ],
                "prefix": "All except:",
                "readOnly": true
              }
            },
            "properties": [
              {
                "id": "custom.hideFrom",
                "value": {
                  "legend": false,
                  "tooltip": false,
                  "viz": true
                }
              }
            ]
          }
        ]
      },
      "gridPos": {
        "h": 8,
        "w": 12,
        "x": 12,
        "y": 0
      },
      "id": 1,
      "options": {
        "legend": {
          "calcs": [],
          "displayMode": "list",
          "placement": "bottom",
          "showLegend": true
        },
        "tooltip": {
          "hideZeros": false,
          "mode": "single",
          "sort": "none"
        }
      },
      "pluginVersion": "12.0.2",
      "targets": [
        {
          "editorMode": "code",
          "format": "table",
          "rawQuery": true,
          "rawSql": "SELECT\n  window_start AS \"time\",\n  SUM(count) AS total_clicks\nFROM clicks_aggregates\nGROUP BY window_start\nORDER BY window_start",
          "refId": "A",
          "sql": {
            "columns": [
              {
                "parameters": [],
                "type": "function"
              }
            ],
            "groupBy": [
              {
                "property": {
                  "type": "string"
                },
                "type": "groupBy"
              }
            ],
            "limit": 50
          }
        }
      ],
      "title": "Total Clicks (10s Window)",
      "type": "timeseries"
    },
    {
      "datasource": {
        "type": "grafana-postgresql-datasource",
        "uid": "eesjj0teoeebke"
      },
      "fieldConfig": {
        "defaults": {
          "color": {
            "mode": "palette-classic"
          },
          "custom": {
            "axisBorderShow": false,
            "axisCenteredZero": false,
            "axisColorMode": "text",
            "axisLabel": "",
            "axisPlacement": "auto",
            "fillOpacity": 80,
            "gradientMode": "none",
            "hideFrom": {
              "legend": false,
              "tooltip": false,
              "viz": false
            },
            "lineWidth": 1,
            "scaleDistribution": {
              "type": "linear"
            },
            "thresholdsStyle": {
              "mode": "off"
            }
          },
          "mappings": [],
          "thresholds": {
            "mode": "absolute",
            "steps": [
              {
                "color": "green"
              },
              {
                "color": "red",
                "value": 80
              }
            ]
          }
        },
        "overrides": [
          {
            "__systemRef": "hideSeriesFrom",
            "matcher": {
              "id": "byNames",
              "options": {
                "mode": "exclude",
                "names": [
                  "total_clicks"
                ],
                "prefix": "All except:",
                "readOnly": true
              }
            },
            "properties": [
              {
                "id": "custom.hideFrom",
                "value": {
                  "legend": false,
                  "tooltip": false,
                  "viz": true
                }
              }
            ]
          }
        ]
      },
      "gridPos": {
        "h": 8,
        "w": 12,
        "x": 6,
        "y": 8
      },
      "id": 2,
      "options": {
        "barRadius": 0,
        "barWidth": 0.97,
        "fullHighlight": false,
        "groupWidth": 0.7,
        "legend": {
          "calcs": [],
          "displayMode": "list",
          "placement": "bottom",
          "showLegend": true
        },
        "orientation": "auto",
        "showValue": "auto",
        "stacking": "none",
        "tooltip": {
          "hideZeros": false,
          "mode": "single",
          "sort": "none"
        },
        "xTickLabelRotation": 0,
        "xTickLabelSpacing": 0
      },
      "pluginVersion": "12.0.2",
      "targets": [
        {
          "editorMode": "code",
          "format": "table",
          "rawQuery": true,
          "rawSql": "SELECT\n  page                AS page,\n  SUM(\"count\")        AS total_clicks\nFROM clicks_aggregates\nWHERE window_start\n  BETWEEN to_timestamp($__from/1000)\n      AND to_timestamp($__to/1000)\nGROUP BY page\nORDER BY total_clicks DESC\nLIMIT 5;",
          "refId": "A",
          "sql": {
            "columns": [
              {
                "parameters": [],
                "type": "function"
              }
            ],
            "groupBy": [
              {
                "property": {
                  "type": "string"
                },
                "type": "groupBy"
              }
            ],
            "limit": 50
          }
        }
      ],
      "title": "Top 5 Pages by Click Volume",
      "type": "barchart"
    }
  ],
  "preload": false,
  "refresh": "10s",
  "schemaVersion": 41,
  "tags": [],
  "templating": {
    "list": []
  },
  "time": {
    "from": "now-5m",
    "to": "now"
  },
  "timepicker": {},
  "timezone": "browser",
  "title": "Realtime-Analytics-Pipeline Dashboard",
  "uid": "406900f0-fa95-47d6-aa59-3d52441cbc7a",
  "version": 16
}